yc1175_indicator/__init__.py
yc1175_indicator/const.py
yc1175_indicator/indicator.py
yc1175_indicator/indicator_cli.py
yc1175_indicator-0.1.1.dist-info/LICENSE
yc1175_indicator-0.1.1.dist-info/METADATA
yc1175_indicator-0.1.1.dist-info/WHEEL
yc1175_indicator-0.1.1.dist-info/entry_points.txt
yc1175_indicator-0.1.1.dist-info/RECORD
