Metadata-Version: 2.1
Name: yc1175-indicator
Version: 0.1.1
Summary: A library to control the yc1175 indicator in Sonoff iHost
Home-page: https://github.com/darkxst/yc1175-indicator
License: MIT
Keywords: yc11752,ihost,indicator
Author: Tim Lunn
Author-email: tim@feathertop.org
Requires-Python: >=3.10,<4.0
Classifier: License :: OSI Approved :: MIT License
Classifier: Programming Language :: Python :: 3
Classifier: Programming Language :: Python :: 3.10
Classifier: Programming Language :: Python :: 3.11
Classifier: Programming Language :: Python :: 3.12
Requires-Dist: crcmod (>=1.7,<2.0)
Requires-Dist: pyserial-asyncio (>=0.6,<0.7)
Project-URL: Repository, https://github.com/darkxst/yc1175-indicator
